<?xml version="1.0" encoding="ISO-8859-1"?>

<!-- ########################################

 # EXTRA300L by PAF team
 # April 2016 : Modified by PAF team
 # http://equipe-flightgear.forumactif.com

##########################################-->

<PropertyList>

  <path>switch.ac</path>

  <animation>
    <type>range</type>
    <min-m>  0 </min-m>
    <max-m> 45 </max-m>
  </animation>

  <animation>
    <object-name>Switch</object-name>
    <object-name>SwitchNut</object-name>
  </animation>

  <animation>
    <type>rotate</type>
    <object-name>Switch</object-name>
    <property>/controls/switches/smoke</property>
    <factor> -70 </factor>
    <axis>
      <x> 0 </x>
      <y> 1 </y>
      <z> 0 </z>
    </axis>
  </animation>

  <animation>
    <type>pick</type>
    <visible>true</visible>
    <object-name>Switch</object-name>
    <action>
      <button>0</button>
      <repeatable>true</repeatable>
      <binding>
        <command>property-toggle</command>
        <property>/controls/switches/smoke</property>
      </binding>
      <binding>
        <command>property-toggle</command>
        <property>sim/model/click</property>
      </binding>
    </action>
  </animation>

</PropertyList>
